pslmw_md_toc_files_plus/__init__.py
pslmw_md_toc_files_plus/logger_config.py
pslmw_md_toc_files_plus/pslmw_md_toc_files_plus.py
pslmw_md_toc_files_plus-1.0.0.dist-info/licenses/LICENSE
pslmw_md_toc_files_plus-1.0.0.dist-info/METADATA
pslmw_md_toc_files_plus-1.0.0.dist-info/WHEEL
pslmw_md_toc_files_plus-1.0.0.dist-info/top_level.txt
pslmw_md_toc_files_plus-1.0.0.dist-info/RECORD
